DSInterface/__init__.py
DSInterface/main.py
DSInterface-0.1rc3.dist-info/METADATA
DSInterface-0.1rc3.dist-info/RECORD
DSInterface-0.1rc3.dist-info/WHEEL
DSInterface-0.1rc3.dist-info/top_level.txt
